[
    {
        "time_minutes": 0,
        "temp_t1": 20.0,
        "temp_t2": 20.0,
        "temp_t3": 20.0,
        "temp_t4": 20.0,
        "temp_t5": 20.0,
        "temp_t6": 20.0,
        "temp_t7": 20.0,
        "temp_t8": 20.0,
        "temp_t9": 20.0
    },
    {
        "time_minutes": 60,
        "temp_t1": 37.222,
        "temp_t2": 28.794,
        "temp_t3": 21.233,
        "temp_t4": 20.074,
        "temp_t5": 20.07,
        "temp_t6": 20.016,
        "temp_t7": 20.001,
        "temp_t8": 20.0,
        "temp_t9": 20.0
    },
    {
        "time_minutes": 120,
        "temp_t1": 56.666,
        "temp_t2": 41.673,
        "temp_t3": 24.251,
        "temp_t4": 20.356,
        "temp_t5": 20.342,
        "temp_t6": 20.09,
        "temp_t7": 20.007,
        "temp_t8": 20.001,
        "temp_t9": 20.0
    },
    {
        "time_minutes": 180,
        "temp_t1": 76.605,
        "temp_t2": 56.349,
        "temp_t3": 28.955,
        "temp_t4": 20.983,
        "temp_t5": 20.955,
        "temp_t6": 20.278,
        "temp_t7": 20.025,
        "temp_t8": 20.002,
        "temp_t9": 20.0
    },
    {
        "time_minutes": 240,
        "temp_t1": 96.561,
        "temp_t2": 71.866,
        "temp_t3": 35.023,
        "temp_t4": 22.054,
        "temp_t5": 22.01,
        "temp_t6": 20.644,
        "temp_t7": 20.07,
        "temp_t8": 20.008,
        "temp_t9": 20.0
    },
    {
        "time_minutes": 300,
        "temp_t1": 116.37,
        "temp_t2": 87.782,
        "temp_t3": 42.126,
        "temp_t4": 23.62,
        "temp_t5": 23.563,
        "temp_t6": 21.239,
        "temp_t7": 20.158,
        "temp_t8": 20.021,
        "temp_t9": 20.0
    },
    {
        "time_minutes": 360,
        "temp_t1": 134.41,
        "temp_t2": 102.6,
        "temp_t3": 49.832,
        "temp_t4": 25.684,
        "temp_t5": 25.621,
        "temp_t6": 22.1,
        "temp_t7": 20.308,
        "temp_t8": 20.046,
        "temp_t9": 20.001
    },
    {
        "time_minutes": 420,
        "temp_t1": 151.11,
        "temp_t2": 115.51,
        "temp_t3": 57.691,
        "temp_t4": 28.206,
        "temp_t5": 28.142,
        "temp_t6": 23.244,
        "temp_t7": 20.542,
        "temp_t8": 20.09,
        "temp_t9": 20.003
    },
    {
        "time_minutes": 480,
        "temp_t1": 167.45,
        "temp_t2": 127.87,
        "temp_t3": 65.463,
        "temp_t4": 31.117,
        "temp_t5": 31.06,
        "temp_t6": 24.669,
        "temp_t7": 20.875,
        "temp_t8": 20.161,
        "temp_t9": 20.006
    },
    {
        "time_minutes": 540,
        "temp_t1": 183.74,
        "temp_t2": 140.56,
        "temp_t3": 73.036,
        "temp_t4": 34.344,
        "temp_t5": 34.3,
        "temp_t6": 26.359,
        "temp_t7": 21.322,
        "temp_t8": 20.268,
        "temp_t9": 20.011
    },
    {
        "time_minutes": 600,
        "temp_t1": 200.14,
        "temp_t2": 153.7,
        "temp_t3": 80.406,
        "temp_t4": 37.82,
        "temp_t5": 37.794,
        "temp_t6": 28.29,
        "temp_t7": 21.892,
        "temp_t8": 20.419,
        "temp_t9": 20.021
    },
    {
        "time_minutes": 660,
        "temp_t1": 216.78,
        "temp_t2": 167.31,
        "temp_t3": 87.612,
        "temp_t4": 41.49,
        "temp_t5": 41.485,
        "temp_t6": 30.436,
        "temp_t7": 22.593,
        "temp_t8": 20.622,
        "temp_t9": 20.036
    },
    {
        "time_minutes": 720,
        "temp_t1": 233.65,
        "temp_t2": 181.38,
        "temp_t3": 94.7,
        "temp_t4": 45.313,
        "temp_t5": 45.331,
        "temp_t6": 32.77,
        "temp_t7": 23.424,
        "temp_t8": 20.885,
        "temp_t9": 20.058
    },
    {
        "time_minutes": 780,
        "temp_t1": 250.68,
        "temp_t2": 195.83,
        "temp_t3": 101.71,
        "temp_t4": 49.26,
        "temp_t5": 49.301,
        "temp_t6": 35.27,
        "temp_t7": 24.386,
        "temp_t8": 21.214,
        "temp_t9": 20.091
    },
    {
        "time_minutes": 840,
        "temp_t1": 267.83,
        "temp_t2": 210.54,
        "temp_t3": 108.72,
        "temp_t4": 53.309,
        "temp_t5": 53.373,
        "temp_t6": 37.916,
        "temp_t7": 25.476,
        "temp_t8": 21.613,
        "temp_t9": 20.137
    },
    {
        "time_minutes": 900,
        "temp_t1": 285.11,
        "temp_t2": 225.42,
        "temp_t3": 115.92,
        "temp_t4": 57.445,
        "temp_t5": 57.53,
        "temp_t6": 40.691,
        "temp_t7": 26.688,
        "temp_t8": 22.087,
        "temp_t9": 20.198
    },
    {
        "time_minutes": 960,
        "temp_t1": 302.49,
        "temp_t2": 240.33,
        "temp_t3": 123.5,
        "temp_t4": 61.659,
        "temp_t5": 61.763,
        "temp_t6": 43.581,
        "temp_t7": 28.019,
        "temp_t8": 22.638,
        "temp_t9": 20.279
    },
    {
        "time_minutes": 1020,
        "temp_t1": 319.98,
        "temp_t2": 255.28,
        "temp_t3": 131.54,
        "temp_t4": 65.942,
        "temp_t5": 66.065,
        "temp_t6": 46.576,
        "temp_t7": 29.463,
        "temp_t8": 23.268,
        "temp_t9": 20.381
    },
    {
        "time_minutes": 1080,
        "temp_t1": 337.6,
        "temp_t2": 270.31,
        "temp_t3": 140.02,
        "temp_t4": 70.287,
        "temp_t5": 70.426,
        "temp_t6": 49.664,
        "temp_t7": 31.013,
        "temp_t8": 23.976,
        "temp_t9": 20.509
    },
    {
        "time_minutes": 1140,
        "temp_t1": 355.36,
        "temp_t2": 285.43,
        "temp_t3": 148.91,
        "temp_t4": 74.69,
        "temp_t5": 74.842,
        "temp_t6": 52.839,
        "temp_t7": 32.665,
        "temp_t8": 24.765,
        "temp_t9": 20.666
    },
    {
        "time_minutes": 1200,
        "temp_t1": 373.27,
        "temp_t2": 300.62,
        "temp_t3": 158.17,
        "temp_t4": 79.153,
        "temp_t5": 79.312,
        "temp_t6": 56.093,
        "temp_t7": 34.412,
        "temp_t8": 25.632,
        "temp_t9": 20.853
    },
    {
        "time_minutes": 1260,
        "temp_t1": 391.34,
        "temp_t2": 315.91,
        "temp_t3": 167.73,
        "temp_t4": 83.67,
        "temp_t5": 83.828,
        "temp_t6": 59.421,
        "temp_t7": 36.25,
        "temp_t8": 26.577,
        "temp_t9": 21.075
    },
    {
        "time_minutes": 1320,
        "temp_t1": 409.58,
        "temp_t2": 331.3,
        "temp_t3": 177.55,
        "temp_t4": 88.243,
        "temp_t5": 88.391,
        "temp_t6": 62.817,
        "temp_t7": 38.173,
        "temp_t8": 27.599,
        "temp_t9": 21.334
    },
    {
        "time_minutes": 1380,
        "temp_t1": 428.0,
        "temp_t2": 346.76,
        "temp_t3": 187.55,
        "temp_t4": 92.866,
        "temp_t5": 92.99,
        "temp_t6": 66.277,
        "temp_t7": 40.176,
        "temp_t8": 28.695,
        "temp_t9": 21.633
    },
    {
        "time_minutes": 1440,
        "temp_t1": 446.58,
        "temp_t2": 362.3,
        "temp_t3": 197.69,
        "temp_t4": 97.533,
        "temp_t5": 97.609,
        "temp_t6": 69.795,
        "temp_t7": 42.256,
        "temp_t8": 29.865,
        "temp_t9": 21.973
    },
    {
        "time_minutes": 1500,
        "temp_t1": 465.31,
        "temp_t2": 377.94,
        "temp_t3": 207.92,
        "temp_t4": 102.23,
        "temp_t5": 102.2,
        "temp_t6": 73.361,
        "temp_t7": 44.407,
        "temp_t8": 31.106,
        "temp_t9": 22.357
    },
    {
        "time_minutes": 1560,
        "temp_t1": 484.16,
        "temp_t2": 393.66,
        "temp_t3": 218.17,
        "temp_t4": 106.96,
        "temp_t5": 106.77,
        "temp_t6": 76.963,
        "temp_t7": 46.623,
        "temp_t8": 32.416,
        "temp_t9": 22.787
    },
    {
        "time_minutes": 1620,
        "temp_t1": 503.08,
        "temp_t2": 409.44,
        "temp_t3": 228.44,
        "temp_t4": 111.74,
        "temp_t5": 111.38,
        "temp_t6": 80.589,
        "temp_t7": 48.901,
        "temp_t8": 33.792,
        "temp_t9": 23.263
    },
    {
        "time_minutes": 1680,
        "temp_t1": 522.0,
        "temp_t2": 425.22,
        "temp_t3": 238.67,
        "temp_t4": 116.61,
        "temp_t5": 116.08,
        "temp_t6": 84.227,
        "temp_t7": 51.232,
        "temp_t8": 35.232,
        "temp_t9": 23.788
    },
    {
        "time_minutes": 1740,
        "temp_t1": 540.83,
        "temp_t2": 440.97,
        "temp_t3": 248.88,
        "temp_t4": 121.61,
        "temp_t5": 120.98,
        "temp_t6": 87.864,
        "temp_t7": 53.611,
        "temp_t8": 36.733,
        "temp_t9": 24.362
    },
    {
        "time_minutes": 1800,
        "temp_t1": 559.43,
        "temp_t2": 456.61,
        "temp_t3": 259.04,
        "temp_t4": 126.76,
        "temp_t5": 126.11,
        "temp_t6": 91.504,
        "temp_t7": 56.033,
        "temp_t8": 38.293,
        "temp_t9": 24.986
    },
    {
        "time_minutes": 1860,
        "temp_t1": 577.71,
        "temp_t2": 472.07,
        "temp_t3": 269.15,
        "temp_t4": 132.09,
        "temp_t5": 131.45,
        "temp_t6": 95.142,
        "temp_t7": 58.493,
        "temp_t8": 39.907,
        "temp_t9": 25.661
    },
    {
        "time_minutes": 1920,
        "temp_t1": 595.52,
        "temp_t2": 487.3,
        "temp_t3": 279.19,
        "temp_t4": 137.58,
        "temp_t5": 136.99,
        "temp_t6": 98.77,
        "temp_t7": 60.985,
        "temp_t8": 41.574,
        "temp_t9": 26.387
    },
    {
        "time_minutes": 1980,
        "temp_t1": 612.74,
        "temp_t2": 502.19,
        "temp_t3": 289.15,
        "temp_t4": 143.23,
        "temp_t5": 142.69,
        "temp_t6": 102.39,
        "temp_t7": 63.506,
        "temp_t8": 43.289,
        "temp_t9": 27.164
    },
    {
        "time_minutes": 2040,
        "temp_t1": 629.28,
        "temp_t2": 516.68,
        "temp_t3": 299.02,
        "temp_t4": 149.01,
        "temp_t5": 148.56,
        "temp_t6": 106.04,
        "temp_t7": 66.052,
        "temp_t8": 45.051,
        "temp_t9": 27.993
    },
    {
        "time_minutes": 2100,
        "temp_t1": 645.03,
        "temp_t2": 530.7,
        "temp_t3": 308.77,
        "temp_t4": 154.92,
        "temp_t5": 154.56,
        "temp_t6": 109.72,
        "temp_t7": 68.62,
        "temp_t8": 46.856,
        "temp_t9": 28.872
    },
    {
        "time_minutes": 2160,
        "temp_t1": 659.95,
        "temp_t2": 544.22,
        "temp_t3": 318.38,
        "temp_t4": 160.93,
        "temp_t5": 160.69,
        "temp_t6": 113.46,
        "temp_t7": 71.206,
        "temp_t8": 48.702,
        "temp_t9": 29.802
    },
    {
        "time_minutes": 2220,
        "temp_t1": 674.01,
        "temp_t2": 557.18,
        "temp_t3": 327.84,
        "temp_t4": 167.04,
        "temp_t5": 166.92,
        "temp_t6": 117.3,
        "temp_t7": 73.807,
        "temp_t8": 50.585,
        "temp_t9": 30.782
    },
    {
        "time_minutes": 2280,
        "temp_t1": 687.22,
        "temp_t2": 569.58,
        "temp_t3": 337.13,
        "temp_t4": 173.23,
        "temp_t5": 173.23,
        "temp_t6": 121.25,
        "temp_t7": 76.42,
        "temp_t8": 52.504,
        "temp_t9": 31.812
    },
    {
        "time_minutes": 2340,
        "temp_t1": 699.6,
        "temp_t2": 581.41,
        "temp_t3": 346.23,
        "temp_t4": 179.46,
        "temp_t5": 179.6,
        "temp_t6": 125.33,
        "temp_t7": 79.042,
        "temp_t8": 54.455,
        "temp_t9": 32.89
    },
    {
        "time_minutes": 2400,
        "temp_t1": 711.19,
        "temp_t2": 592.69,
        "temp_t3": 355.15,
        "temp_t4": 185.75,
        "temp_t5": 186.02,
        "temp_t6": 129.52,
        "temp_t7": 81.669,
        "temp_t8": 56.436,
        "temp_t9": 34.015
    },
    {
        "time_minutes": 2460,
        "temp_t1": 722.04,
        "temp_t2": 603.41,
        "temp_t3": 363.86,
        "temp_t4": 192.05,
        "temp_t5": 192.45,
        "temp_t6": 133.82,
        "temp_t7": 84.299,
        "temp_t8": 58.444,
        "temp_t9": 35.186
    },
    {
        "time_minutes": 2520,
        "temp_t1": 732.2,
        "temp_t2": 613.62,
        "temp_t3": 372.38,
        "temp_t4": 198.35,
        "temp_t5": 198.87,
        "temp_t6": 138.23,
        "temp_t7": 86.928,
        "temp_t8": 60.478,
        "temp_t9": 36.403
    },
    {
        "time_minutes": 2580,
        "temp_t1": 741.72,
        "temp_t2": 623.32,
        "temp_t3": 380.7,
        "temp_t4": 204.64,
        "temp_t5": 205.26,
        "temp_t6": 142.73,
        "temp_t7": 89.552,
        "temp_t8": 62.534,
        "temp_t9": 37.664
    },
    {
        "time_minutes": 2640,
        "temp_t1": 750.64,
        "temp_t2": 632.58,
        "temp_t3": 388.83,
        "temp_t4": 210.9,
        "temp_t5": 211.61,
        "temp_t6": 147.33,
        "temp_t7": 92.172,
        "temp_t8": 64.61,
        "temp_t9": 38.967
    },
    {
        "time_minutes": 2700,
        "temp_t1": 759.04,
        "temp_t2": 641.41,
        "temp_t3": 396.75,
        "temp_t4": 217.11,
        "temp_t5": 217.9,
        "temp_t6": 151.99,
        "temp_t7": 94.779,
        "temp_t8": 66.704,
        "temp_t9": 40.312
    },
    {
        "time_minutes": 2760,
        "temp_t1": 766.95,
        "temp_t2": 649.83,
        "temp_t3": 404.49,
        "temp_t4": 223.27,
        "temp_t5": 224.12,
        "temp_t6": 156.72,
        "temp_t7": 97.372,
        "temp_t8": 68.812,
        "temp_t9": 41.697
    },
    {
        "time_minutes": 2820,
        "temp_t1": 774.43,
        "temp_t2": 657.87,
        "temp_t3": 412.04,
        "temp_t4": 229.36,
        "temp_t5": 230.26,
        "temp_t6": 161.51,
        "temp_t7": 99.952,
        "temp_t8": 70.934,
        "temp_t9": 43.12
    },
    {
        "time_minutes": 2880,
        "temp_t1": 781.52,
        "temp_t2": 665.55,
        "temp_t3": 419.4,
        "temp_t4": 235.38,
        "temp_t5": 236.33,
        "temp_t6": 166.34,
        "temp_t7": 102.53,
        "temp_t8": 73.065,
        "temp_t9": 44.579
    },
    {
        "time_minutes": 2940,
        "temp_t1": 788.25,
        "temp_t2": 672.91,
        "temp_t3": 426.57,
        "temp_t4": 241.34,
        "temp_t5": 242.33,
        "temp_t6": 171.2,
        "temp_t7": 105.1,
        "temp_t8": 75.204,
        "temp_t9": 46.074
    },
    {
        "time_minutes": 3000,
        "temp_t1": 794.64,
        "temp_t2": 679.98,
        "temp_t3": 433.57,
        "temp_t4": 247.22,
        "temp_t5": 248.25,
        "temp_t6": 176.08,
        "temp_t7": 107.7,
        "temp_t8": 77.348,
        "temp_t9": 47.603
    },
    {
        "time_minutes": 3060,
        "temp_t1": 800.75,
        "temp_t2": 686.78,
        "temp_t3": 440.39,
        "temp_t4": 253.03,
        "temp_t5": 254.09,
        "temp_t6": 180.98,
        "temp_t7": 110.33,
        "temp_t8": 79.493,
        "temp_t9": 49.163
    },
    {
        "time_minutes": 3120,
        "temp_t1": 806.58,
        "temp_t2": 693.31,
        "temp_t3": 447.05,
        "temp_t4": 258.76,
        "temp_t5": 259.86,
        "temp_t6": 185.88,
        "temp_t7": 113.01,
        "temp_t8": 81.64,
        "temp_t9": 50.754
    },
    {
        "time_minutes": 3180,
        "temp_t1": 812.18,
        "temp_t2": 699.62,
        "temp_t3": 453.55,
        "temp_t4": 264.42,
        "temp_t5": 265.55,
        "temp_t6": 190.77,
        "temp_t7": 115.74,
        "temp_t8": 83.782,
        "temp_t9": 52.373
    },
    {
        "time_minutes": 3240,
        "temp_t1": 817.56,
        "temp_t2": 705.7,
        "temp_t3": 459.89,
        "temp_t4": 270.01,
        "temp_t5": 271.16,
        "temp_t6": 195.65,
        "temp_t7": 118.55,
        "temp_t8": 85.917,
        "temp_t9": 54.019
    },
    {
        "time_minutes": 3300,
        "temp_t1": 822.74,
        "temp_t2": 711.58,
        "temp_t3": 466.1,
        "temp_t4": 275.52,
        "temp_t5": 276.7,
        "temp_t6": 200.5,
        "temp_t7": 121.44,
        "temp_t8": 88.043,
        "temp_t9": 55.69
    },
    {
        "time_minutes": 3360,
        "temp_t1": 827.73,
        "temp_t2": 717.27,
        "temp_t3": 472.17,
        "temp_t4": 280.96,
        "temp_t5": 282.17,
        "temp_t6": 205.33,
        "temp_t7": 124.4,
        "temp_t8": 90.159,
        "temp_t9": 57.383
    },
    {
        "time_minutes": 3420,
        "temp_t1": 832.54,
        "temp_t2": 722.79,
        "temp_t3": 478.1,
        "temp_t4": 286.33,
        "temp_t5": 287.56,
        "temp_t6": 210.13,
        "temp_t7": 127.43,
        "temp_t8": 92.26,
        "temp_t9": 59.098
    },
    {
        "time_minutes": 3480,
        "temp_t1": 837.17,
        "temp_t2": 728.15,
        "temp_t3": 483.91,
        "temp_t4": 291.63,
        "temp_t5": 292.88,
        "temp_t6": 214.89,
        "temp_t7": 130.53,
        "temp_t8": 94.34,
        "temp_t9": 60.831
    },
    {
        "time_minutes": 3540,
        "temp_t1": 841.66,
        "temp_t2": 733.36,
        "temp_t3": 489.61,
        "temp_t4": 296.86,
        "temp_t5": 298.13,
        "temp_t6": 219.61,
        "temp_t7": 133.69,
        "temp_t8": 96.398,
        "temp_t9": 62.582
    },
    {
        "time_minutes": 3600,
        "temp_t1": 846.01,
        "temp_t2": 738.42,
        "temp_t3": 495.2,
        "temp_t4": 302.02,
        "temp_t5": 303.31,
        "temp_t6": 224.29,
        "temp_t7": 136.92,
        "temp_t8": 98.433,
        "temp_t9": 64.348
    },
    {
        "time_minutes": 3660,
        "temp_t1": 850.22,
        "temp_t2": 743.35,
        "temp_t3": 500.67,
        "temp_t4": 307.12,
        "temp_t5": 308.43,
        "temp_t6": 228.93,
        "temp_t7": 140.2,
        "temp_t8": 100.45,
        "temp_t9": 66.126
    },
    {
        "time_minutes": 3720,
        "temp_t1": 854.31,
        "temp_t2": 748.13,
        "temp_t3": 506.04,
        "temp_t4": 312.14,
        "temp_t5": 313.48,
        "temp_t6": 233.52,
        "temp_t7": 143.53,
        "temp_t8": 102.45,
        "temp_t9": 67.916
    },
    {
        "time_minutes": 3780,
        "temp_t1": 858.29,
        "temp_t2": 752.79,
        "temp_t3": 511.31,
        "temp_t4": 317.11,
        "temp_t5": 318.46,
        "temp_t6": 238.08,
        "temp_t7": 146.91,
        "temp_t8": 104.45,
        "temp_t9": 69.714
    },
    {
        "time_minutes": 3840,
        "temp_t1": 862.16,
        "temp_t2": 757.32,
        "temp_t3": 516.48,
        "temp_t4": 322.01,
        "temp_t5": 323.37,
        "temp_t6": 242.59,
        "temp_t7": 150.34,
        "temp_t8": 106.45,
        "temp_t9": 71.518
    },
    {
        "time_minutes": 3900,
        "temp_t1": 865.92,
        "temp_t2": 761.75,
        "temp_t3": 521.54,
        "temp_t4": 326.85,
        "temp_t5": 328.23,
        "temp_t6": 247.06,
        "temp_t7": 153.8,
        "temp_t8": 108.46,
        "temp_t9": 73.326
    },
    {
        "time_minutes": 3960,
        "temp_t1": 869.59,
        "temp_t2": 766.07,
        "temp_t3": 526.52,
        "temp_t4": 331.62,
        "temp_t5": 333.02,
        "temp_t6": 251.49,
        "temp_t7": 157.3,
        "temp_t8": 110.49,
        "temp_t9": 75.135
    },
    {
        "time_minutes": 4020,
        "temp_t1": 873.16,
        "temp_t2": 770.3,
        "temp_t3": 531.41,
        "temp_t4": 336.34,
        "temp_t5": 337.75,
        "temp_t6": 255.88,
        "temp_t7": 160.83,
        "temp_t8": 112.56,
        "temp_t9": 76.944
    },
    {
        "time_minutes": 4080,
        "temp_t1": 876.64,
        "temp_t2": 774.44,
        "temp_t3": 536.22,
        "temp_t4": 340.99,
        "temp_t5": 342.42,
        "temp_t6": 260.23,
        "temp_t7": 164.39,
        "temp_t8": 114.67,
        "temp_t9": 78.748
    },
    {
        "time_minutes": 4140,
        "temp_t1": 880.04,
        "temp_t2": 778.5,
        "temp_t3": 540.95,
        "temp_t4": 345.59,
        "temp_t5": 347.03,
        "temp_t6": 264.54,
        "temp_t7": 167.97,
        "temp_t8": 116.82,
        "temp_t9": 80.546
    },
    {
        "time_minutes": 4200,
        "temp_t1": 883.36,
        "temp_t2": 782.46,
        "temp_t3": 545.59,
        "temp_t4": 350.14,
        "temp_t5": 351.59,
        "temp_t6": 268.8,
        "temp_t7": 171.57,
        "temp_t8": 119.04,
        "temp_t9": 82.335
    },
    {
        "time_minutes": 4260,
        "temp_t1": 886.61,
        "temp_t2": 786.34,
        "temp_t3": 550.16,
        "temp_t4": 354.63,
        "temp_t5": 356.09,
        "temp_t6": 273.03,
        "temp_t7": 175.18,
        "temp_t8": 121.31,
        "temp_t9": 84.11
    },
    {
        "time_minutes": 4320,
        "temp_t1": 889.79,
        "temp_t2": 790.13,
        "temp_t3": 554.66,
        "temp_t4": 359.06,
        "temp_t5": 360.54,
        "temp_t6": 277.22,
        "temp_t7": 178.8,
        "temp_t8": 123.63,
        "temp_t9": 85.869
    },
    {
        "time_minutes": 4380,
        "temp_t1": 892.9,
        "temp_t2": 793.85,
        "temp_t3": 559.09,
        "temp_t4": 363.45,
        "temp_t5": 364.93,
        "temp_t6": 281.37,
        "temp_t7": 182.43,
        "temp_t8": 126.01,
        "temp_t9": 87.607
    },
    {
        "time_minutes": 4440,
        "temp_t1": 895.95,
        "temp_t2": 797.5,
        "temp_t3": 563.45,
        "temp_t4": 367.78,
        "temp_t5": 369.28,
        "temp_t6": 285.49,
        "temp_t7": 186.06,
        "temp_t8": 128.45,
        "temp_t9": 89.32
    },
    {
        "time_minutes": 4500,
        "temp_t1": 898.9,
        "temp_t2": 801.06,
        "temp_t3": 567.74,
        "temp_t4": 372.07,
        "temp_t5": 373.57,
        "temp_t6": 289.57,
        "temp_t7": 189.69,
        "temp_t8": 130.93,
        "temp_t9": 91.002
    },
    {
        "time_minutes": 4560,
        "temp_t1": 901.71,
        "temp_t2": 804.53,
        "temp_t3": 571.97,
        "temp_t4": 376.3,
        "temp_t5": 377.82,
        "temp_t6": 293.61,
        "temp_t7": 193.31,
        "temp_t8": 133.47,
        "temp_t9": 92.649
    },
    {
        "time_minutes": 4620,
        "temp_t1": 904.42,
        "temp_t2": 807.91,
        "temp_t3": 576.13,
        "temp_t4": 380.5,
        "temp_t5": 382.02,
        "temp_t6": 297.61,
        "temp_t7": 196.92,
        "temp_t8": 136.05,
        "temp_t9": 94.254
    },
    {
        "time_minutes": 4680,
        "temp_t1": 907.06,
        "temp_t2": 811.2,
        "temp_t3": 580.23,
        "temp_t4": 384.64,
        "temp_t5": 386.18,
        "temp_t6": 301.58,
        "temp_t7": 200.52,
        "temp_t8": 138.68,
        "temp_t9": 95.806
    },
    {
        "time_minutes": 4740,
        "temp_t1": 909.62,
        "temp_t2": 814.41,
        "temp_t3": 584.27,
        "temp_t4": 388.74,
        "temp_t5": 390.29,
        "temp_t6": 305.52,
        "temp_t7": 204.11,
        "temp_t8": 141.35,
        "temp_t9": 97.296
    },
    {
        "time_minutes": 4800,
        "temp_t1": 912.12,
        "temp_t2": 817.55,
        "temp_t3": 588.25,
        "temp_t4": 392.8,
        "temp_t5": 394.36,
        "temp_t6": 309.42,
        "temp_t7": 207.68,
        "temp_t8": 144.07,
        "temp_t9": 98.718
    },
    {
        "time_minutes": 4860,
        "temp_t1": 914.57,
        "temp_t2": 820.62,
        "temp_t3": 592.17,
        "temp_t4": 396.82,
        "temp_t5": 398.38,
        "temp_t6": 313.29,
        "temp_t7": 211.24,
        "temp_t8": 146.82,
        "temp_t9": 100.09
    },
    {
        "time_minutes": 4920,
        "temp_t1": 916.97,
        "temp_t2": 823.63,
        "temp_t3": 596.03,
        "temp_t4": 400.79,
        "temp_t5": 402.37,
        "temp_t6": 317.12,
        "temp_t7": 214.78,
        "temp_t8": 149.61,
        "temp_t9": 101.41
    },
    {
        "time_minutes": 4980,
        "temp_t1": 919.33,
        "temp_t2": 826.59,
        "temp_t3": 599.83,
        "temp_t4": 404.72,
        "temp_t5": 406.31,
        "temp_t6": 320.92,
        "temp_t7": 218.29,
        "temp_t8": 152.44,
        "temp_t9": 102.69
    },
    {
        "time_minutes": 5040,
        "temp_t1": 921.65,
        "temp_t2": 829.5,
        "temp_t3": 603.58,
        "temp_t4": 408.62,
        "temp_t5": 410.21,
        "temp_t6": 324.68,
        "temp_t7": 221.79,
        "temp_t8": 155.3,
        "temp_t9": 103.95
    },
    {
        "time_minutes": 5100,
        "temp_t1": 923.93,
        "temp_t2": 832.37,
        "temp_t3": 607.28,
        "temp_t4": 412.47,
        "temp_t5": 414.07,
        "temp_t6": 328.41,
        "temp_t7": 225.26,
        "temp_t8": 158.19,
        "temp_t9": 105.18
    },
    {
        "time_minutes": 5160,
        "temp_t1": 926.17,
        "temp_t2": 835.18,
        "temp_t3": 610.92,
        "temp_t4": 416.28,
        "temp_t5": 417.89,
        "temp_t6": 332.11,
        "temp_t7": 228.72,
        "temp_t8": 161.11,
        "temp_t9": 106.41
    },
    {
        "time_minutes": 5220,
        "temp_t1": 928.38,
        "temp_t2": 837.95,
        "temp_t3": 614.52,
        "temp_t4": 420.05,
        "temp_t5": 421.67,
        "temp_t6": 335.78,
        "temp_t7": 232.15,
        "temp_t8": 164.05,
        "temp_t9": 107.63
    },
    {
        "time_minutes": 5280,
        "temp_t1": 930.56,
        "temp_t2": 840.67,
        "temp_t3": 618.07,
        "temp_t4": 423.79,
        "temp_t5": 425.41,
        "temp_t6": 339.41,
        "temp_t7": 235.56,
        "temp_t8": 167.02,
        "temp_t9": 108.85
    },
    {
        "time_minutes": 5340,
        "temp_t1": 932.7,
        "temp_t2": 843.35,
        "temp_t3": 621.57,
        "temp_t4": 427.48,
        "temp_t5": 429.12,
        "temp_t6": 343.02,
        "temp_t7": 238.96,
        "temp_t8": 170.0,
        "temp_t9": 110.08
    },
    {
        "time_minutes": 5400,
        "temp_t1": 934.81,
        "temp_t2": 845.99,
        "temp_t3": 625.03,
        "temp_t4": 431.15,
        "temp_t5": 432.79,
        "temp_t6": 346.59,
        "temp_t7": 242.33,
        "temp_t8": 173.01,
        "temp_t9": 111.32
    },
    {
        "time_minutes": 5460,
        "temp_t1": 936.9,
        "temp_t2": 848.59,
        "temp_t3": 628.45,
        "temp_t4": 434.77,
        "temp_t5": 436.42,
        "temp_t6": 350.14,
        "temp_t7": 245.68,
        "temp_t8": 176.03,
        "temp_t9": 112.59
    },
    {
        "time_minutes": 5520,
        "temp_t1": 938.96,
        "temp_t2": 851.16,
        "temp_t3": 631.83,
        "temp_t4": 438.36,
        "temp_t5": 440.01,
        "temp_t6": 353.66,
        "temp_t7": 249.02,
        "temp_t8": 179.07,
        "temp_t9": 113.89
    },
    {
        "time_minutes": 5580,
        "temp_t1": 940.99,
        "temp_t2": 853.69,
        "temp_t3": 635.16,
        "temp_t4": 441.91,
        "temp_t5": 443.57,
        "temp_t6": 357.15,
        "temp_t7": 252.33,
        "temp_t8": 182.11,
        "temp_t9": 115.23
    },
    {
        "time_minutes": 5640,
        "temp_t1": 942.99,
        "temp_t2": 856.2,
        "temp_t3": 638.45,
        "temp_t4": 445.44,
        "temp_t5": 447.1,
        "temp_t6": 360.61,
        "temp_t7": 255.63,
        "temp_t8": 185.17,
        "temp_t9": 116.61
    },
    {
        "time_minutes": 5700,
        "temp_t1": 944.97,
        "temp_t2": 858.67,
        "temp_t3": 641.7,
        "temp_t4": 448.92,
        "temp_t5": 450.6,
        "temp_t6": 364.05,
        "temp_t7": 258.91,
        "temp_t8": 188.23,
        "temp_t9": 118.05
    },
    {
        "time_minutes": 5760,
        "temp_t1": 946.93,
        "temp_t2": 861.11,
        "temp_t3": 644.92,
        "temp_t4": 452.38,
        "temp_t5": 454.06,
        "temp_t6": 367.46,
        "temp_t7": 262.17,
        "temp_t8": 191.29,
        "temp_t9": 119.55
    },
    {
        "time_minutes": 5820,
        "temp_t1": 948.86,
        "temp_t2": 863.51,
        "temp_t3": 648.1,
        "temp_t4": 455.81,
        "temp_t5": 457.49,
        "temp_t6": 370.84,
        "temp_t7": 265.41,
        "temp_t8": 194.35,
        "temp_t9": 121.09
    },
    {
        "time_minutes": 5880,
        "temp_t1": 950.77,
        "temp_t2": 865.89,
        "temp_t3": 651.25,
        "temp_t4": 459.2,
        "temp_t5": 460.89,
        "temp_t6": 374.2,
        "temp_t7": 268.63,
        "temp_t8": 197.41,
        "temp_t9": 122.69
    },
    {
        "time_minutes": 5940,
        "temp_t1": 952.65,
        "temp_t2": 868.24,
        "temp_t3": 654.36,
        "temp_t4": 462.57,
        "temp_t5": 464.26,
        "temp_t6": 377.53,
        "temp_t7": 271.83,
        "temp_t8": 200.47,
        "temp_t9": 124.35
    },
    {
        "time_minutes": 6000,
        "temp_t1": 954.52,
        "temp_t2": 870.56,
        "temp_t3": 657.45,
        "temp_t4": 465.9,
        "temp_t5": 467.61,
        "temp_t6": 380.84,
        "temp_t7": 275.02,
        "temp_t8": 203.52,
        "temp_t9": 126.06
    },
    {
        "time_minutes": 6060,
        "temp_t1": 956.36,
        "temp_t2": 872.86,
        "temp_t3": 660.49,
        "temp_t4": 469.21,
        "temp_t5": 470.92,
        "temp_t6": 384.12,
        "temp_t7": 278.19,
        "temp_t8": 206.56,
        "temp_t9": 127.83
    },
    {
        "time_minutes": 6120,
        "temp_t1": 958.17,
        "temp_t2": 875.13,
        "temp_t3": 663.51,
        "temp_t4": 472.49,
        "temp_t5": 474.2,
        "temp_t6": 387.38,
        "temp_t7": 281.34,
        "temp_t8": 209.6,
        "temp_t9": 129.66
    },
    {
        "time_minutes": 6180,
        "temp_t1": 959.97,
        "temp_t2": 877.38,
        "temp_t3": 666.5,
        "temp_t4": 475.74,
        "temp_t5": 477.46,
        "temp_t6": 390.62,
        "temp_t7": 284.48,
        "temp_t8": 212.63,
        "temp_t9": 131.55
    },
    {
        "time_minutes": 6240,
        "temp_t1": 961.75,
        "temp_t2": 879.6,
        "temp_t3": 669.46,
        "temp_t4": 478.97,
        "temp_t5": 480.69,
        "temp_t6": 393.84,
        "temp_t7": 287.6,
        "temp_t8": 215.65,
        "temp_t9": 133.5
    },
    {
        "time_minutes": 6300,
        "temp_t1": 963.51,
        "temp_t2": 881.79,
        "temp_t3": 672.39,
        "temp_t4": 482.17,
        "temp_t5": 483.9,
        "temp_t6": 397.03,
        "temp_t7": 290.7,
        "temp_t8": 218.66,
        "temp_t9": 135.5
    },
    {
        "time_minutes": 6360,
        "temp_t1": 965.26,
        "temp_t2": 883.96,
        "temp_t3": 675.29,
        "temp_t4": 485.34,
        "temp_t5": 487.08,
        "temp_t6": 400.21,
        "temp_t7": 293.79,
        "temp_t8": 221.66,
        "temp_t9": 137.57
    },
    {
        "time_minutes": 6420,
        "temp_t1": 966.98,
        "temp_t2": 886.11,
        "temp_t3": 678.16,
        "temp_t4": 488.49,
        "temp_t5": 490.23,
        "temp_t6": 403.36,
        "temp_t7": 296.86,
        "temp_t8": 224.65,
        "temp_t9": 139.7
    },
    {
        "time_minutes": 6480,
        "temp_t1": 968.68,
        "temp_t2": 888.24,
        "temp_t3": 681.01,
        "temp_t4": 491.62,
        "temp_t5": 493.36,
        "temp_t6": 406.49,
        "temp_t7": 299.92,
        "temp_t8": 227.63,
        "temp_t9": 141.89
    },
    {
        "time_minutes": 6540,
        "temp_t1": 970.37,
        "temp_t2": 890.34,
        "temp_t3": 683.83,
        "temp_t4": 494.72,
        "temp_t5": 496.47,
        "temp_t6": 409.6,
        "temp_t7": 302.96,
        "temp_t8": 230.6,
        "temp_t9": 144.14
    },
    {
        "time_minutes": 6600,
        "temp_t1": 972.04,
        "temp_t2": 892.42,
        "temp_t3": 686.63,
        "temp_t4": 497.8,
        "temp_t5": 499.55,
        "temp_t6": 412.69,
        "temp_t7": 305.99,
        "temp_t8": 233.57,
        "temp_t9": 146.46
    },
    {
        "time_minutes": 6660,
        "temp_t1": 973.69,
        "temp_t2": 894.48,
        "temp_t3": 689.39,
        "temp_t4": 500.85,
        "temp_t5": 502.61,
        "temp_t6": 415.76,
        "temp_t7": 309.0,
        "temp_t8": 236.52,
        "temp_t9": 148.83
    },
    {
        "time_minutes": 6720,
        "temp_t1": 975.33,
        "temp_t2": 896.51,
        "temp_t3": 692.14,
        "temp_t4": 503.88,
        "temp_t5": 505.64,
        "temp_t6": 418.8,
        "temp_t7": 312.0,
        "temp_t8": 239.47,
        "temp_t9": 151.27
    },
    {
        "time_minutes": 6780,
        "temp_t1": 976.95,
        "temp_t2": 898.53,
        "temp_t3": 694.86,
        "temp_t4": 506.89,
        "temp_t5": 508.66,
        "temp_t6": 421.83,
        "temp_t7": 314.98,
        "temp_t8": 242.4,
        "temp_t9": 153.77
    },
    {
        "time_minutes": 6840,
        "temp_t1": 978.55,
        "temp_t2": 900.53,
        "temp_t3": 697.56,
        "temp_t4": 509.88,
        "temp_t5": 511.65,
        "temp_t6": 424.84,
        "temp_t7": 317.95,
        "temp_t8": 245.33,
        "temp_t9": 156.34
    },
    {
        "time_minutes": 6900,
        "temp_t1": 980.14,
        "temp_t2": 902.5,
        "temp_t3": 700.24,
        "temp_t4": 512.85,
        "temp_t5": 514.62,
        "temp_t6": 427.83,
        "temp_t7": 320.9,
        "temp_t8": 248.26,
        "temp_t9": 158.96
    },
    {
        "time_minutes": 6960,
        "temp_t1": 981.71,
        "temp_t2": 904.46,
        "temp_t3": 702.9,
        "temp_t4": 515.79,
        "temp_t5": 517.56,
        "temp_t6": 430.8,
        "temp_t7": 323.84,
        "temp_t8": 251.17,
        "temp_t9": 161.65
    },
    {
        "time_minutes": 7020,
        "temp_t1": 983.26,
        "temp_t2": 906.4,
        "temp_t3": 705.53,
        "temp_t4": 518.71,
        "temp_t5": 520.49,
        "temp_t6": 433.75,
        "temp_t7": 326.77,
        "temp_t8": 254.08,
        "temp_t9": 164.4
    },
    {
        "time_minutes": 7080,
        "temp_t1": 984.81,
        "temp_t2": 908.32,
        "temp_t3": 708.14,
        "temp_t4": 521.61,
        "temp_t5": 523.39,
        "temp_t6": 436.68,
        "temp_t7": 329.68,
        "temp_t8": 256.98,
        "temp_t9": 167.21
    },
    {
        "time_minutes": 7140,
        "temp_t1": 986.33,
        "temp_t2": 910.23,
        "temp_t3": 710.72,
        "temp_t4": 524.5,
        "temp_t5": 526.28,
        "temp_t6": 439.6,
        "temp_t7": 332.58,
        "temp_t8": 259.87,
        "temp_t9": 170.08
    },
    {
        "time_minutes": 7200,
        "temp_t1": 987.85,
        "temp_t2": 912.11,
        "temp_t3": 713.29,
        "temp_t4": 527.36,
        "temp_t5": 529.14,
        "temp_t6": 442.5,
        "temp_t7": 335.47,
        "temp_t8": 262.76,
        "temp_t9": 173.0
    },
    {
        "time_minutes": 7260,
        "temp_t1": 989.35,
        "temp_t2": 913.98,
        "temp_t3": 715.83,
        "temp_t4": 530.2,
        "temp_t5": 531.99,
        "temp_t6": 445.38,
        "temp_t7": 338.34,
        "temp_t8": 265.64,
        "temp_t9": 175.99
    },
    {
        "time_minutes": 7320,
        "temp_t1": 990.83,
        "temp_t2": 915.83,
        "temp_t3": 718.36,
        "temp_t4": 533.02,
        "temp_t5": 534.81,
        "temp_t6": 448.25,
        "temp_t7": 341.21,
        "temp_t8": 268.52,
        "temp_t9": 179.03
    },
    {
        "time_minutes": 7380,
        "temp_t1": 992.31,
        "temp_t2": 917.66,
        "temp_t3": 720.86,
        "temp_t4": 535.83,
        "temp_t5": 537.62,
        "temp_t6": 451.1,
        "temp_t7": 344.06,
        "temp_t8": 271.39,
        "temp_t9": 182.12
    },
    {
        "time_minutes": 7440,
        "temp_t1": 993.77,
        "temp_t2": 919.47,
        "temp_t3": 723.34,
        "temp_t4": 538.61,
        "temp_t5": 540.4,
        "temp_t6": 453.93,
        "temp_t7": 346.9,
        "temp_t8": 274.25,
        "temp_t9": 185.26
    },
    {
        "time_minutes": 7500,
        "temp_t1": 995.21,
        "temp_t2": 921.27,
        "temp_t3": 725.8,
        "temp_t4": 541.38,
        "temp_t5": 543.17,
        "temp_t6": 456.75,
        "temp_t7": 349.73,
        "temp_t8": 277.11,
        "temp_t9": 188.44
    },
    {
        "time_minutes": 7560,
        "temp_t1": 996.65,
        "temp_t2": 923.06,
        "temp_t3": 728.25,
        "temp_t4": 544.12,
        "temp_t5": 545.92,
        "temp_t6": 459.55,
        "temp_t7": 352.55,
        "temp_t8": 279.97,
        "temp_t9": 191.67
    },
    {
        "time_minutes": 7620,
        "temp_t1": 998.07,
        "temp_t2": 924.82,
        "temp_t3": 730.67,
        "temp_t4": 546.86,
        "temp_t5": 548.66,
        "temp_t6": 462.34,
        "temp_t7": 355.35,
        "temp_t8": 282.81,
        "temp_t9": 194.92
    },
    {
        "time_minutes": 7680,
        "temp_t1": 999.48,
        "temp_t2": 926.57,
        "temp_t3": 733.07,
        "temp_t4": 549.57,
        "temp_t5": 551.37,
        "temp_t6": 465.12,
        "temp_t7": 358.15,
        "temp_t8": 285.66,
        "temp_t9": 198.2
    },
    {
        "time_minutes": 7740,
        "temp_t1": 1000.9,
        "temp_t2": 928.31,
        "temp_t3": 735.45,
        "temp_t4": 552.27,
        "temp_t5": 554.07,
        "temp_t6": 467.88,
        "temp_t7": 360.94,
        "temp_t8": 288.49,
        "temp_t9": 201.5
    },
    {
        "time_minutes": 7800,
        "temp_t1": 1002.3,
        "temp_t2": 930.02,
        "temp_t3": 737.82,
        "temp_t4": 554.95,
        "temp_t5": 556.75,
        "temp_t6": 470.62,
        "temp_t7": 363.71,
        "temp_t8": 291.32,
        "temp_t9": 204.81
    },
    {
        "time_minutes": 7860,
        "temp_t1": 1003.6,
        "temp_t2": 931.73,
        "temp_t3": 740.17,
        "temp_t4": 557.61,
        "temp_t5": 559.42,
        "temp_t6": 473.35,
        "temp_t7": 366.48,
        "temp_t8": 294.15,
        "temp_t9": 208.12
    },
    {
        "time_minutes": 7920,
        "temp_t1": 1005.0,
        "temp_t2": 933.42,
        "temp_t3": 742.51,
        "temp_t4": 560.26,
        "temp_t5": 562.07,
        "temp_t6": 476.07,
        "temp_t7": 369.24,
        "temp_t8": 296.97,
        "temp_t9": 211.44
    },
    {
        "time_minutes": 7980,
        "temp_t1": 1006.3,
        "temp_t2": 935.09,
        "temp_t3": 744.82,
        "temp_t4": 562.89,
        "temp_t5": 564.7,
        "temp_t6": 478.78,
        "temp_t7": 371.99,
        "temp_t8": 299.78,
        "temp_t9": 214.74
    },
    {
        "time_minutes": 8040,
        "temp_t1": 1007.7,
        "temp_t2": 936.76,
        "temp_t3": 747.12,
        "temp_t4": 565.5,
        "temp_t5": 567.32,
        "temp_t6": 481.47,
        "temp_t7": 374.73,
        "temp_t8": 302.59,
        "temp_t9": 218.03
    },
    {
        "time_minutes": 8100,
        "temp_t1": 1009.0,
        "temp_t2": 938.41,
        "temp_t3": 749.41,
        "temp_t4": 568.11,
        "temp_t5": 569.92,
        "temp_t6": 484.15,
        "temp_t7": 377.46,
        "temp_t8": 305.39,
        "temp_t9": 221.29
    },
    {
        "time_minutes": 8160,
        "temp_t1": 1010.3,
        "temp_t2": 940.04,
        "temp_t3": 751.67,
        "temp_t4": 570.69,
        "temp_t5": 572.51,
        "temp_t6": 486.82,
        "temp_t7": 380.18,
        "temp_t8": 308.19,
        "temp_t9": 224.53
    },
    {
        "time_minutes": 8220,
        "temp_t1": 1011.6,
        "temp_t2": 941.67,
        "temp_t3": 753.92,
        "temp_t4": 573.27,
        "temp_t5": 575.08,
        "temp_t6": 489.47,
        "temp_t7": 382.89,
        "temp_t8": 310.98,
        "temp_t9": 227.74
    },
    {
        "time_minutes": 8280,
        "temp_t1": 1012.9,
        "temp_t2": 943.28,
        "temp_t3": 756.16,
        "temp_t4": 575.82,
        "temp_t5": 577.64,
        "temp_t6": 492.12,
        "temp_t7": 385.59,
        "temp_t8": 313.76,
        "temp_t9": 230.93
    },
    {
        "time_minutes": 8340,
        "temp_t1": 1014.2,
        "temp_t2": 944.88,
        "temp_t3": 758.38,
        "temp_t4": 578.37,
        "temp_t5": 580.19,
        "temp_t6": 494.75,
        "temp_t7": 388.29,
        "temp_t8": 316.53,
        "temp_t9": 234.09
    },
    {
        "time_minutes": 8400,
        "temp_t1": 1015.5,
        "temp_t2": 946.46,
        "temp_t3": 760.58,
        "temp_t4": 580.9,
        "temp_t5": 582.72,
        "temp_t6": 497.37,
        "temp_t7": 390.97,
        "temp_t8": 319.3,
        "temp_t9": 237.21
    },
    {
        "time_minutes": 8460,
        "temp_t1": 1016.8,
        "temp_t2": 948.04,
        "temp_t3": 762.77,
        "temp_t4": 583.41,
        "temp_t5": 585.24,
        "temp_t6": 499.97,
        "temp_t7": 393.65,
        "temp_t8": 322.06,
        "temp_t9": 240.31
    },
    {
        "time_minutes": 8520,
        "temp_t1": 1018.0,
        "temp_t2": 949.6,
        "temp_t3": 764.95,
        "temp_t4": 585.92,
        "temp_t5": 587.75,
        "temp_t6": 502.57,
        "temp_t7": 396.32,
        "temp_t8": 324.8,
        "temp_t9": 243.37
    },
    {
        "time_minutes": 8580,
        "temp_t1": 1019.3,
        "temp_t2": 951.15,
        "temp_t3": 767.11,
        "temp_t4": 588.41,
        "temp_t5": 590.24,
        "temp_t6": 505.15,
        "temp_t7": 398.98,
        "temp_t8": 327.54,
        "temp_t9": 246.41
    },
    {
        "time_minutes": 8640,
        "temp_t1": 1020.5,
        "temp_t2": 952.68,
        "temp_t3": 769.26,
        "temp_t4": 590.89,
        "temp_t5": 592.72,
        "temp_t6": 507.73,
        "temp_t7": 401.64,
        "temp_t8": 330.27,
        "temp_t9": 249.42
    },
    {
        "time_minutes": 8700,
        "temp_t1": 1021.7,
        "temp_t2": 954.2,
        "temp_t3": 771.39,
        "temp_t4": 593.35,
        "temp_t5": 595.18,
        "temp_t6": 510.29,
        "temp_t7": 404.28,
        "temp_t8": 332.99,
        "temp_t9": 252.41
    },
    {
        "time_minutes": 8760,
        "temp_t1": 1022.9,
        "temp_t2": 955.72,
        "temp_t3": 773.51,
        "temp_t4": 595.8,
        "temp_t5": 597.64,
        "temp_t6": 512.84,
        "temp_t7": 406.92,
        "temp_t8": 335.7,
        "temp_t9": 255.36
    },
    {
        "time_minutes": 8820,
        "temp_t1": 1024.2,
        "temp_t2": 957.22,
        "temp_t3": 775.62,
        "temp_t4": 598.24,
        "temp_t5": 600.08,
        "temp_t6": 515.37,
        "temp_t7": 409.54,
        "temp_t8": 338.4,
        "temp_t9": 258.3
    },
    {
        "time_minutes": 8880,
        "temp_t1": 1025.4,
        "temp_t2": 958.71,
        "temp_t3": 777.72,
        "temp_t4": 600.67,
        "temp_t5": 602.51,
        "temp_t6": 517.9,
        "temp_t7": 412.16,
        "temp_t8": 341.08,
        "temp_t9": 261.21
    },
    {
        "time_minutes": 8940,
        "temp_t1": 1026.5,
        "temp_t2": 960.19,
        "temp_t3": 779.8,
        "temp_t4": 603.09,
        "temp_t5": 604.92,
        "temp_t6": 520.41,
        "temp_t7": 414.77,
        "temp_t8": 343.76,
        "temp_t9": 264.09
    },
    {
        "time_minutes": 9000,
        "temp_t1": 1027.7,
        "temp_t2": 961.66,
        "temp_t3": 781.87,
        "temp_t4": 605.49,
        "temp_t5": 607.33,
        "temp_t6": 522.92,
        "temp_t7": 417.36,
        "temp_t8": 346.43,
        "temp_t9": 266.96
    },
    {
        "time_minutes": 9060,
        "temp_t1": 1028.9,
        "temp_t2": 963.12,
        "temp_t3": 783.92,
        "temp_t4": 607.88,
        "temp_t5": 609.72,
        "temp_t6": 525.41,
        "temp_t7": 419.95,
        "temp_t8": 349.09,
        "temp_t9": 269.8
    },
    {
        "time_minutes": 9120,
        "temp_t1": 1030.1,
        "temp_t2": 964.57,
        "temp_t3": 785.97,
        "temp_t4": 610.26,
        "temp_t5": 612.1,
        "temp_t6": 527.89,
        "temp_t7": 422.53,
        "temp_t8": 351.73,
        "temp_t9": 272.62
    },
    {
        "time_minutes": 9180,
        "temp_t1": 1031.2,
        "temp_t2": 966.01,
        "temp_t3": 788.0,
        "temp_t4": 612.63,
        "temp_t5": 614.47,
        "temp_t6": 530.36,
        "temp_t7": 425.1,
        "temp_t8": 354.37,
        "temp_t9": 275.42
    },
    {
        "time_minutes": 9240,
        "temp_t1": 1032.4,
        "temp_t2": 967.44,
        "temp_t3": 790.01,
        "temp_t4": 614.99,
        "temp_t5": 616.83,
        "temp_t6": 532.82,
        "temp_t7": 427.66,
        "temp_t8": 356.99,
        "temp_t9": 278.21
    },
    {
        "time_minutes": 9300,
        "temp_t1": 1033.5,
        "temp_t2": 968.87,
        "temp_t3": 792.02,
        "temp_t4": 617.33,
        "temp_t5": 619.17,
        "temp_t6": 535.27,
        "temp_t7": 430.21,
        "temp_t8": 359.6,
        "temp_t9": 280.97
    },
    {
        "time_minutes": 9360,
        "temp_t1": 1034.7,
        "temp_t2": 970.28,
        "temp_t3": 794.02,
        "temp_t4": 619.67,
        "temp_t5": 621.51,
        "temp_t6": 537.71,
        "temp_t7": 432.75,
        "temp_t8": 362.21,
        "temp_t9": 283.71
    },
    {
        "time_minutes": 9420,
        "temp_t1": 1035.8,
        "temp_t2": 971.68,
        "temp_t3": 796.01,
        "temp_t4": 621.99,
        "temp_t5": 623.83,
        "temp_t6": 540.14,
        "temp_t7": 435.28,
        "temp_t8": 364.8,
        "temp_t9": 286.44
    },
    {
        "time_minutes": 9480,
        "temp_t1": 1036.9,
        "temp_t2": 973.08,
        "temp_t3": 797.99,
        "temp_t4": 624.3,
        "temp_t5": 626.14,
        "temp_t6": 542.56,
        "temp_t7": 437.8,
        "temp_t8": 367.38,
        "temp_t9": 289.15
    },
    {
        "time_minutes": 9540,
        "temp_t1": 1038.0,
        "temp_t2": 974.46,
        "temp_t3": 799.95,
        "temp_t4": 626.6,
        "temp_t5": 628.44,
        "temp_t6": 544.96,
        "temp_t7": 440.31,
        "temp_t8": 369.95,
        "temp_t9": 291.85
    },
    {
        "time_minutes": 9600,
        "temp_t1": 1039.1,
        "temp_t2": 975.83,
        "temp_t3": 801.91,
        "temp_t4": 628.89,
        "temp_t5": 630.73,
        "temp_t6": 547.36,
        "temp_t7": 442.81,
        "temp_t8": 372.51,
        "temp_t9": 294.52
    },
    {
        "time_minutes": 9660,
        "temp_t1": 1040.2,
        "temp_t2": 977.2,
        "temp_t3": 803.85,
        "temp_t4": 631.16,
        "temp_t5": 633.01,
        "temp_t6": 549.75,
        "temp_t7": 445.3,
        "temp_t8": 375.06,
        "temp_t9": 297.19
    },
    {
        "time_minutes": 9720,
        "temp_t1": 1041.3,
        "temp_t2": 978.55,
        "temp_t3": 805.79,
        "temp_t4": 633.43,
        "temp_t5": 635.27,
        "temp_t6": 552.13,
        "temp_t7": 447.78,
        "temp_t8": 377.6,
        "temp_t9": 299.83
    },
    {
        "time_minutes": 9780,
        "temp_t1": 1042.4,
        "temp_t2": 979.9,
        "temp_t3": 807.71,
        "temp_t4": 635.69,
        "temp_t5": 637.53,
        "temp_t6": 554.49,
        "temp_t7": 450.25,
        "temp_t8": 380.13,
        "temp_t9": 302.46
    },
    {
        "time_minutes": 9840,
        "temp_t1": 1043.5,
        "temp_t2": 981.24,
        "temp_t3": 809.62,
        "temp_t4": 637.93,
        "temp_t5": 639.77,
        "temp_t6": 556.85,
        "temp_t7": 452.71,
        "temp_t8": 382.65,
        "temp_t9": 305.08
    },
    {
        "time_minutes": 9900,
        "temp_t1": 1044.5,
        "temp_t2": 982.57,
        "temp_t3": 811.51,
        "temp_t4": 640.17,
        "temp_t5": 642.01,
        "temp_t6": 559.2,
        "temp_t7": 455.17,
        "temp_t8": 385.16,
        "temp_t9": 307.68
    },
    {
        "time_minutes": 9960,
        "temp_t1": 1045.6,
        "temp_t2": 983.89,
        "temp_t3": 813.4,
        "temp_t4": 642.39,
        "temp_t5": 644.23,
        "temp_t6": 561.54,
        "temp_t7": 457.61,
        "temp_t8": 387.66,
        "temp_t9": 310.27
    },
    {
        "time_minutes": 10020,
        "temp_t1": 1046.6,
        "temp_t2": 985.21,
        "temp_t3": 815.28,
        "temp_t4": 644.61,
        "temp_t5": 646.45,
        "temp_t6": 563.87,
        "temp_t7": 460.04,
        "temp_t8": 390.14,
        "temp_t9": 312.84
    },
    {
        "time_minutes": 10080,
        "temp_t1": 1047.7,
        "temp_t2": 986.51,
        "temp_t3": 817.14,
        "temp_t4": 646.81,
        "temp_t5": 648.65,
        "temp_t6": 566.18,
        "temp_t7": 462.47,
        "temp_t8": 392.62,
        "temp_t9": 315.4
    },
    {
        "time_minutes": 10140,
        "temp_t1": 1048.7,
        "temp_t2": 987.81,
        "temp_t3": 818.99,
        "temp_t4": 649.0,
        "temp_t5": 650.85,
        "temp_t6": 568.49,
        "temp_t7": 464.88,
        "temp_t8": 395.09,
        "temp_t9": 317.94
    },
    {
        "time_minutes": 10200,
        "temp_t1": 1049.8,
        "temp_t2": 989.1,
        "temp_t3": 820.84,
        "temp_t4": 651.19,
        "temp_t5": 653.03,
        "temp_t6": 570.79,
        "temp_t7": 467.29,
        "temp_t8": 397.56,
        "temp_t9": 320.48
    },
    {
        "time_minutes": 10260,
        "temp_t1": 1050.8,
        "temp_t2": 990.38,
        "temp_t3": 822.67,
        "temp_t4": 653.36,
        "temp_t5": 655.2,
        "temp_t6": 573.08,
        "temp_t7": 469.69,
        "temp_t8": 400.01,
        "temp_t9": 322.99
    },
    {
        "time_minutes": 10320,
        "temp_t1": 1051.8,
        "temp_t2": 991.65,
        "temp_t3": 824.49,
        "temp_t4": 655.53,
        "temp_t5": 657.37,
        "temp_t6": 575.36,
        "temp_t7": 472.07,
        "temp_t8": 402.45,
        "temp_t9": 325.5
    },
    {
        "time_minutes": 10380,
        "temp_t1": 1052.8,
        "temp_t2": 992.92,
        "temp_t3": 826.31,
        "temp_t4": 657.68,
        "temp_t5": 659.52,
        "temp_t6": 577.64,
        "temp_t7": 474.45,
        "temp_t8": 404.88,
        "temp_t9": 327.99
    },
    {
        "time_minutes": 10440,
        "temp_t1": 1053.8,
        "temp_t2": 994.18,
        "temp_t3": 828.11,
        "temp_t4": 659.83,
        "temp_t5": 661.67,
        "temp_t6": 579.9,
        "temp_t7": 476.82,
        "temp_t8": 407.31,
        "temp_t9": 330.47
    },
    {
        "time_minutes": 10500,
        "temp_t1": 1054.8,
        "temp_t2": 995.43,
        "temp_t3": 829.91,
        "temp_t4": 661.96,
        "temp_t5": 663.8,
        "temp_t6": 582.15,
        "temp_t7": 479.19,
        "temp_t8": 409.72,
        "temp_t9": 332.94
    },
    {
        "time_minutes": 10560,
        "temp_t1": 1055.8,
        "temp_t2": 996.67,
        "temp_t3": 831.69,
        "temp_t4": 664.09,
        "temp_t5": 665.93,
        "temp_t6": 584.4,
        "temp_t7": 481.54,
        "temp_t8": 412.13,
        "temp_t9": 335.4
    },
    {
        "time_minutes": 10620,
        "temp_t1": 1056.8,
        "temp_t2": 997.91,
        "temp_t3": 833.47,
        "temp_t4": 666.21,
        "temp_t5": 668.05,
        "temp_t6": 586.64,
        "temp_t7": 483.88,
        "temp_t8": 414.52,
        "temp_t9": 337.84
    },
    {
        "time_minutes": 10680,
        "temp_t1": 1057.8,
        "temp_t2": 999.14,
        "temp_t3": 835.24,
        "temp_t4": 668.31,
        "temp_t5": 670.16,
        "temp_t6": 588.86,
        "temp_t7": 486.22,
        "temp_t8": 416.91,
        "temp_t9": 340.27
    },
    {
        "time_minutes": 10740,
        "temp_t1": 1058.8,
        "temp_t2": 1000.4,
        "temp_t3": 836.99,
        "temp_t4": 670.41,
        "temp_t5": 672.25,
        "temp_t6": 591.08,
        "temp_t7": 488.54,
        "temp_t8": 419.28,
        "temp_t9": 342.69
    },
    {
        "time_minutes": 10800,
        "temp_t1": 1059.8,
        "temp_t2": 1001.6,
        "temp_t3": 838.74,
        "temp_t4": 672.5,
        "temp_t5": 674.34,
        "temp_t6": 593.29,
        "temp_t7": 490.86,
        "temp_t8": 421.65,
        "temp_t9": 345.1
    },
    {
        "time_minutes": 10860,
        "temp_t1": 1060.7,
        "temp_t2": 1002.8,
        "temp_t3": 840.47,
        "temp_t4": 674.58,
        "temp_t5": 676.43,
        "temp_t6": 595.49,
        "temp_t7": 493.17,
        "temp_t8": 424.01,
        "temp_t9": 347.5
    },
    {
        "time_minutes": 10920,
        "temp_t1": 1061.7,
        "temp_t2": 1004.0,
        "temp_t3": 842.2,
        "temp_t4": 676.65,
        "temp_t5": 678.5,
        "temp_t6": 597.69,
        "temp_t7": 495.47,
        "temp_t8": 426.36,
        "temp_t9": 349.89
    },
    {
        "time_minutes": 10980,
        "temp_t1": 1062.6,
        "temp_t2": 1005.2,
        "temp_t3": 843.92,
        "temp_t4": 678.72,
        "temp_t5": 680.56,
        "temp_t6": 599.87,
        "temp_t7": 497.77,
        "temp_t8": 428.7,
        "temp_t9": 352.26
    },
    {
        "time_minutes": 11040,
        "temp_t1": 1063.6,
        "temp_t2": 1006.4,
        "temp_t3": 845.63,
        "temp_t4": 680.77,
        "temp_t5": 682.61,
        "temp_t6": 602.04,
        "temp_t7": 500.05,
        "temp_t8": 431.03,
        "temp_t9": 354.63
    },
    {
        "time_minutes": 11100,
        "temp_t1": 1064.5,
        "temp_t2": 1007.5,
        "temp_t3": 847.33,
        "temp_t4": 682.82,
        "temp_t5": 684.66,
        "temp_t6": 604.21,
        "temp_t7": 502.33,
        "temp_t8": 433.35,
        "temp_t9": 356.98
    },
    {
        "time_minutes": 11160,
        "temp_t1": 1065.5,
        "temp_t2": 1008.7,
        "temp_t3": 849.02,
        "temp_t4": 684.86,
        "temp_t5": 686.7,
        "temp_t6": 606.37,
        "temp_t7": 504.59,
        "temp_t8": 435.66,
        "temp_t9": 359.33
    },
    {
        "time_minutes": 11220,
        "temp_t1": 1066.4,
        "temp_t2": 1009.9,
        "temp_t3": 850.7,
        "temp_t4": 686.88,
        "temp_t5": 688.73,
        "temp_t6": 608.52,
        "temp_t7": 506.85,
        "temp_t8": 437.97,
        "temp_t9": 361.66
    },
    {
        "time_minutes": 11280,
        "temp_t1": 1067.3,
        "temp_t2": 1011.0,
        "temp_t3": 852.38,
        "temp_t4": 688.9,
        "temp_t5": 690.75,
        "temp_t6": 610.66,
        "temp_t7": 509.1,
        "temp_t8": 440.26,
        "temp_t9": 363.99
    },
    {
        "time_minutes": 11340,
        "temp_t1": 1068.3,
        "temp_t2": 1012.2,
        "temp_t3": 854.05,
        "temp_t4": 690.92,
        "temp_t5": 692.76,
        "temp_t6": 612.79,
        "temp_t7": 511.34,
        "temp_t8": 442.55,
        "temp_t9": 366.3
    },
    {
        "time_minutes": 11400,
        "temp_t1": 1069.2,
        "temp_t2": 1013.3,
        "temp_t3": 855.7,
        "temp_t4": 692.92,
        "temp_t5": 694.76,
        "temp_t6": 614.91,
        "temp_t7": 513.57,
        "temp_t8": 444.83,
        "temp_t9": 368.61
    },
    {
        "time_minutes": 11460,
        "temp_t1": 1070.1,
        "temp_t2": 1014.5,
        "temp_t3": 857.35,
        "temp_t4": 694.91,
        "temp_t5": 696.76,
        "temp_t6": 617.02,
        "temp_t7": 515.8,
        "temp_t8": 447.1,
        "temp_t9": 370.91
    },
    {
        "time_minutes": 11520,
        "temp_t1": 1071.0,
        "temp_t2": 1015.6,
        "temp_t3": 858.99,
        "temp_t4": 696.9,
        "temp_t5": 698.74,
        "temp_t6": 619.13,
        "temp_t7": 518.01,
        "temp_t8": 449.36,
        "temp_t9": 373.19
    },
    {
        "time_minutes": 11580,
        "temp_t1": 1071.9,
        "temp_t2": 1016.7,
        "temp_t3": 860.62,
        "temp_t4": 698.88,
        "temp_t5": 700.72,
        "temp_t6": 621.22,
        "temp_t7": 520.22,
        "temp_t8": 451.61,
        "temp_t9": 375.47
    },
    {
        "time_minutes": 11640,
        "temp_t1": 1072.8,
        "temp_t2": 1017.8,
        "temp_t3": 862.25,
        "temp_t4": 700.85,
        "temp_t5": 702.69,
        "temp_t6": 623.31,
        "temp_t7": 522.42,
        "temp_t8": 453.86,
        "temp_t9": 377.74
    },
    {
        "time_minutes": 11700,
        "temp_t1": 1073.7,
        "temp_t2": 1018.9,
        "temp_t3": 863.86,
        "temp_t4": 702.81,
        "temp_t5": 704.66,
        "temp_t6": 625.39,
        "temp_t7": 524.61,
        "temp_t8": 456.1,
        "temp_t9": 380.0
    },
    {
        "time_minutes": 11760,
        "temp_t1": 1074.6,
        "temp_t2": 1020.1,
        "temp_t3": 865.47,
        "temp_t4": 704.77,
        "temp_t5": 706.61,
        "temp_t6": 627.46,
        "temp_t7": 526.79,
        "temp_t8": 458.33,
        "temp_t9": 382.26
    },
    {
        "time_minutes": 11820,
        "temp_t1": 1075.5,
        "temp_t2": 1021.2,
        "temp_t3": 867.07,
        "temp_t4": 706.72,
        "temp_t5": 708.56,
        "temp_t6": 629.52,
        "temp_t7": 528.96,
        "temp_t8": 460.55,
        "temp_t9": 384.5
    },
    {
        "time_minutes": 11880,
        "temp_t1": 1076.4,
        "temp_t2": 1022.2,
        "temp_t3": 868.67,
        "temp_t4": 708.65,
        "temp_t5": 710.49,
        "temp_t6": 631.58,
        "temp_t7": 531.13,
        "temp_t8": 462.76,
        "temp_t9": 386.74
    },
    {
        "time_minutes": 11940,
        "temp_t1": 1077.2,
        "temp_t2": 1023.3,
        "temp_t3": 870.26,
        "temp_t4": 710.58,
        "temp_t5": 712.42,
        "temp_t6": 633.62,
        "temp_t7": 533.28,
        "temp_t8": 464.97,
        "temp_t9": 388.96
    },
    {
        "time_minutes": 12000,
        "temp_t1": 1078.1,
        "temp_t2": 1024.4,
        "temp_t3": 871.83,
        "temp_t4": 712.51,
        "temp_t5": 714.34,
        "temp_t6": 635.66,
        "temp_t7": 535.43,
        "temp_t8": 467.17,
        "temp_t9": 391.19
    },
    {
        "time_minutes": 12060,
        "temp_t1": 1079.0,
        "temp_t2": 1025.5,
        "temp_t3": 873.41,
        "temp_t4": 714.42,
        "temp_t5": 716.26,
        "temp_t6": 637.69,
        "temp_t7": 537.57,
        "temp_t8": 469.36,
        "temp_t9": 393.4
    },
    {
        "time_minutes": 12120,
        "temp_t1": 1079.8,
        "temp_t2": 1026.6,
        "temp_t3": 874.97,
        "temp_t4": 716.33,
        "temp_t5": 718.16,
        "temp_t6": 639.71,
        "temp_t7": 539.71,
        "temp_t8": 471.54,
        "temp_t9": 395.61
    },
    {
        "time_minutes": 12180,
        "temp_t1": 1080.7,
        "temp_t2": 1027.6,
        "temp_t3": 876.52,
        "temp_t4": 718.23,
        "temp_t5": 720.06,
        "temp_t6": 641.73,
        "temp_t7": 541.83,
        "temp_t8": 473.72,
        "temp_t9": 397.8
    },
    {
        "time_minutes": 12240,
        "temp_t1": 1081.5,
        "temp_t2": 1028.7,
        "temp_t3": 878.07,
        "temp_t4": 720.12,
        "temp_t5": 721.95,
        "temp_t6": 643.73,
        "temp_t7": 543.95,
        "temp_t8": 475.89,
        "temp_t9": 400.0
    },
    {
        "time_minutes": 12300,
        "temp_t1": 1082.4,
        "temp_t2": 1029.7,
        "temp_t3": 879.61,
        "temp_t4": 722.0,
        "temp_t5": 723.83,
        "temp_t6": 645.73,
        "temp_t7": 546.06,
        "temp_t8": 478.05,
        "temp_t9": 402.18
    },
    {
        "time_minutes": 12360,
        "temp_t1": 1083.2,
        "temp_t2": 1030.8,
        "temp_t3": 881.14,
        "temp_t4": 723.87,
        "temp_t5": 725.7,
        "temp_t6": 647.72,
        "temp_t7": 548.16,
        "temp_t8": 480.21,
        "temp_t9": 404.36
    },
    {
        "time_minutes": 12420,
        "temp_t1": 1084.1,
        "temp_t2": 1031.8,
        "temp_t3": 882.67,
        "temp_t4": 725.74,
        "temp_t5": 727.57,
        "temp_t6": 649.71,
        "temp_t7": 550.26,
        "temp_t8": 482.35,
        "temp_t9": 406.54
    },
    {
        "time_minutes": 12480,
        "temp_t1": 1084.9,
        "temp_t2": 1032.9,
        "temp_t3": 884.19,
        "temp_t4": 727.6,
        "temp_t5": 729.43,
        "temp_t6": 651.68,
        "temp_t7": 552.35,
        "temp_t8": 484.49,
        "temp_t9": 408.71
    },
    {
        "time_minutes": 12540,
        "temp_t1": 1085.7,
        "temp_t2": 1033.9,
        "temp_t3": 885.7,
        "temp_t4": 729.45,
        "temp_t5": 731.28,
        "temp_t6": 653.65,
        "temp_t7": 554.43,
        "temp_t8": 486.63,
        "temp_t9": 410.87
    },
    {
        "time_minutes": 12600,
        "temp_t1": 1086.5,
        "temp_t2": 1034.9,
        "temp_t3": 887.2,
        "temp_t4": 731.29,
        "temp_t5": 733.12,
        "temp_t6": 655.61,
        "temp_t7": 556.5,
        "temp_t8": 488.75,
        "temp_t9": 413.02
    },
    {
        "time_minutes": 12660,
        "temp_t1": 1087.4,
        "temp_t2": 1035.9,
        "temp_t3": 888.7,
        "temp_t4": 733.13,
        "temp_t5": 734.95,
        "temp_t6": 657.56,
        "temp_t7": 558.56,
        "temp_t8": 490.87,
        "temp_t9": 415.17
    },
    {
        "time_minutes": 12720,
        "temp_t1": 1088.2,
        "temp_t2": 1036.9,
        "temp_t3": 890.2,
        "temp_t4": 734.96,
        "temp_t5": 736.78,
        "temp_t6": 659.51,
        "temp_t7": 560.62,
        "temp_t8": 492.99,
        "temp_t9": 417.31
    },
    {
        "time_minutes": 12780,
        "temp_t1": 1089.0,
        "temp_t2": 1037.9,
        "temp_t3": 891.68,
        "temp_t4": 736.78,
        "temp_t5": 738.6,
        "temp_t6": 661.45,
        "temp_t7": 562.67,
        "temp_t8": 495.09,
        "temp_t9": 419.45
    },
    {
        "time_minutes": 12840,
        "temp_t1": 1089.8,
        "temp_t2": 1038.9,
        "temp_t3": 893.16,
        "temp_t4": 738.59,
        "temp_t5": 740.41,
        "temp_t6": 663.38,
        "temp_t7": 564.72,
        "temp_t8": 497.19,
        "temp_t9": 421.58
    },
    {
        "time_minutes": 12900,
        "temp_t1": 1090.6,
        "temp_t2": 1039.9,
        "temp_t3": 894.63,
        "temp_t4": 740.39,
        "temp_t5": 742.22,
        "temp_t6": 665.3,
        "temp_t7": 566.75,
        "temp_t8": 499.29,
        "temp_t9": 423.7
    },
    {
        "time_minutes": 12960,
        "temp_t1": 1091.4,
        "temp_t2": 1040.9,
        "temp_t3": 896.1,
        "temp_t4": 742.19,
        "temp_t5": 744.01,
        "temp_t6": 667.22,
        "temp_t7": 568.78,
        "temp_t8": 501.37,
        "temp_t9": 425.82
    },
    {
        "time_minutes": 13020,
        "temp_t1": 1092.2,
        "temp_t2": 1041.9,
        "temp_t3": 897.56,
        "temp_t4": 743.98,
        "temp_t5": 745.8,
        "temp_t6": 669.13,
        "temp_t7": 570.81,
        "temp_t8": 503.45,
        "temp_t9": 427.93
    },
    {
        "time_minutes": 13080,
        "temp_t1": 1093.0,
        "temp_t2": 1042.9,
        "temp_t3": 899.01,
        "temp_t4": 745.77,
        "temp_t5": 747.59,
        "temp_t6": 671.03,
        "temp_t7": 572.82,
        "temp_t8": 505.53,
        "temp_t9": 430.04
    },
    {
        "time_minutes": 13140,
        "temp_t1": 1093.8,
        "temp_t2": 1043.9,
        "temp_t3": 900.45,
        "temp_t4": 747.54,
        "temp_t5": 749.36,
        "temp_t6": 672.93,
        "temp_t7": 574.83,
        "temp_t8": 507.59,
        "temp_t9": 432.14
    },
    {
        "time_minutes": 13200,
        "temp_t1": 1094.6,
        "temp_t2": 1044.9,
        "temp_t3": 901.89,
        "temp_t4": 749.31,
        "temp_t5": 751.13,
        "temp_t6": 674.82,
        "temp_t7": 576.84,
        "temp_t8": 509.65,
        "temp_t9": 434.23
    },
    {
        "time_minutes": 13260,
        "temp_t1": 1095.3,
        "temp_t2": 1045.8,
        "temp_t3": 903.32,
        "temp_t4": 751.08,
        "temp_t5": 752.89,
        "temp_t6": 676.7,
        "temp_t7": 578.83,
        "temp_t8": 511.7,
        "temp_t9": 436.32
    },
    {
        "time_minutes": 13320,
        "temp_t1": 1096.1,
        "temp_t2": 1046.8,
        "temp_t3": 904.74,
        "temp_t4": 752.83,
        "temp_t5": 754.64,
        "temp_t6": 678.58,
        "temp_t7": 580.82,
        "temp_t8": 513.75,
        "temp_t9": 438.4
    },
    {
        "time_minutes": 13380,
        "temp_t1": 1096.9,
        "temp_t2": 1047.7,
        "temp_t3": 906.16,
        "temp_t4": 754.58,
        "temp_t5": 756.39,
        "temp_t6": 680.45,
        "temp_t7": 582.81,
        "temp_t8": 515.79,
        "temp_t9": 440.48
    },
    {
        "time_minutes": 13440,
        "temp_t1": 1097.7,
        "temp_t2": 1048.7,
        "temp_t3": 907.57,
        "temp_t4": 756.32,
        "temp_t5": 758.13,
        "temp_t6": 682.31,
        "temp_t7": 584.78,
        "temp_t8": 517.82,
        "temp_t9": 442.55
    },
    {
        "time_minutes": 13500,
        "temp_t1": 1098.4,
        "temp_t2": 1049.6,
        "temp_t3": 908.97,
        "temp_t4": 758.06,
        "temp_t5": 759.87,
        "temp_t6": 684.17,
        "temp_t7": 586.75,
        "temp_t8": 519.84,
        "temp_t9": 444.62
    },
    {
        "time_minutes": 13560,
        "temp_t1": 1099.2,
        "temp_t2": 1050.6,
        "temp_t3": 910.37,
        "temp_t4": 759.78,
        "temp_t5": 761.59,
        "temp_t6": 686.02,
        "temp_t7": 588.72,
        "temp_t8": 521.86,
        "temp_t9": 446.67
    },
    {
        "time_minutes": 13620,
        "temp_t1": 1100.0,
        "temp_t2": 1051.5,
        "temp_t3": 911.76,
        "temp_t4": 761.5,
        "temp_t5": 763.31,
        "temp_t6": 687.86,
        "temp_t7": 590.68,
        "temp_t8": 523.87,
        "temp_t9": 448.73
    },
    {
        "time_minutes": 13680,
        "temp_t1": 1100.7,
        "temp_t2": 1052.5,
        "temp_t3": 913.14,
        "temp_t4": 763.22,
        "temp_t5": 765.03,
        "temp_t6": 689.7,
        "temp_t7": 592.63,
        "temp_t8": 525.88,
        "temp_t9": 450.77
    },
    {
        "time_minutes": 13740,
        "temp_t1": 1101.5,
        "temp_t2": 1053.4,
        "temp_t3": 914.52,
        "temp_t4": 764.93,
        "temp_t5": 766.73,
        "temp_t6": 691.53,
        "temp_t7": 594.57,
        "temp_t8": 527.88,
        "temp_t9": 452.81
    },
    {
        "time_minutes": 13800,
        "temp_t1": 1102.2,
        "temp_t2": 1054.3,
        "temp_t3": 915.89,
        "temp_t4": 766.63,
        "temp_t5": 768.43,
        "temp_t6": 693.35,
        "temp_t7": 596.51,
        "temp_t8": 529.87,
        "temp_t9": 454.85
    },
    {
        "time_minutes": 13860,
        "temp_t1": 1103.0,
        "temp_t2": 1055.2,
        "temp_t3": 917.26,
        "temp_t4": 768.32,
        "temp_t5": 770.13,
        "temp_t6": 695.17,
        "temp_t7": 598.45,
        "temp_t8": 531.86,
        "temp_t9": 456.88
    },
    {
        "time_minutes": 13920,
        "temp_t1": 1103.7,
        "temp_t2": 1056.2,
        "temp_t3": 918.62,
        "temp_t4": 770.01,
        "temp_t5": 771.81,
        "temp_t6": 696.98,
        "temp_t7": 600.37,
        "temp_t8": 533.84,
        "temp_t9": 458.9
    },
    {
        "time_minutes": 13980,
        "temp_t1": 1104.4,
        "temp_t2": 1057.1,
        "temp_t3": 919.97,
        "temp_t4": 771.69,
        "temp_t5": 773.49,
        "temp_t6": 698.79,
        "temp_t7": 602.29,
        "temp_t8": 535.81,
        "temp_t9": 460.92
    },
    {
        "time_minutes": 14040,
        "temp_t1": 1105.2,
        "temp_t2": 1058.0,
        "temp_t3": 921.31,
        "temp_t4": 773.37,
        "temp_t5": 775.17,
        "temp_t6": 700.59,
        "temp_t7": 604.21,
        "temp_t8": 537.78,
        "temp_t9": 462.93
    },
    {
        "time_minutes": 14100,
        "temp_t1": 1105.9,
        "temp_t2": 1058.9,
        "temp_t3": 922.66,
        "temp_t4": 775.04,
        "temp_t5": 776.84,
        "temp_t6": 702.38,
        "temp_t7": 606.12,
        "temp_t8": 539.74,
        "temp_t9": 464.94
    },
    {
        "time_minutes": 14160,
        "temp_t1": 1106.6,
        "temp_t2": 1059.8,
        "temp_t3": 923.99,
        "temp_t4": 776.7,
        "temp_t5": 778.5,
        "temp_t6": 704.16,
        "temp_t7": 608.02,
        "temp_t8": 541.7,
        "temp_t9": 466.94
    },
    {
        "time_minutes": 14220,
        "temp_t1": 1107.4,
        "temp_t2": 1060.7,
        "temp_t3": 925.32,
        "temp_t4": 778.36,
        "temp_t5": 780.15,
        "temp_t6": 705.94,
        "temp_t7": 609.91,
        "temp_t8": 543.65,
        "temp_t9": 468.93
    },
    {
        "time_minutes": 14280,
        "temp_t1": 1108.1,
        "temp_t2": 1061.6,
        "temp_t3": 926.64,
        "temp_t4": 780.01,
        "temp_t5": 781.8,
        "temp_t6": 707.72,
        "temp_t7": 611.8,
        "temp_t8": 545.59,
        "temp_t9": 470.92
    },
    {
        "time_minutes": 14340,
        "temp_t1": 1108.8,
        "temp_t2": 1062.4,
        "temp_t3": 927.95,
        "temp_t4": 781.65,
        "temp_t5": 783.45,
        "temp_t6": 709.48,
        "temp_t7": 613.68,
        "temp_t8": 547.53,
        "temp_t9": 472.9
    },
    {
        "time_minutes": 14400,
        "temp_t1": 1109.5,
        "temp_t2": 1063.3,
        "temp_t3": 929.26,
        "temp_t4": 783.29,
        "temp_t5": 785.09,
        "temp_t6": 711.24,
        "temp_t7": 615.56,
        "temp_t8": 549.46,
        "temp_t9": 474.88
    }
]